gazetteer/KD_Tree.py
gazetteer/__init__.py
gazetteer/pytest.ini
gazetteer/reverse_geocode.py
gazetteer/data/data.db
gazetteer/data/geo-boundaries.csv
python_gazetteer-0.1.1.dist-info/METADATA
python_gazetteer-0.1.1.dist-info/WHEEL
python_gazetteer-0.1.1.dist-info/licenses/LICENSE
python_gazetteer-0.1.1.dist-info/RECORD
