Metadata-Version: 2.4
Name: python-gazetteer
Version: 0.1.1
Summary: A simple, fast and accurate boundary based reverse geocoding library in python
License-File: LICENSE
Requires-Python: >=3.12
Requires-Dist: pydantic>=2.12.5
Requires-Dist: scipy>=1.16.3
Requires-Dist: shapely>=2.1.2
